setup.py
PYPTTESTJSON.egg-info/PKG-INFO
PYPTTESTJSON.egg-info/SOURCES.txt
PYPTTESTJSON.egg-info/dependency_links.txt
PYPTTESTJSON.egg-info/top_level.txt
pypitestjson/__init__.py
pypitestjson/pypitestjson.py