Metadata-Version: 1.0
Name: PYPTTESTJSON
Version: 0.0.0
Summary: charlie private tools
Home-page: UNKNOWN
Author: Charlie
Author-email: lcyuanjiang@sina.com
License: UNKNOWN
Platform: UNKNOWN
